{"message":"","today":"2020-06-16","seleList":[{"poweroffId":2019090231020170,"sgpoweroffId":null,"subsName":"","lineName":"10kV田湾G265线","pubTranName":"双陈村计家坝西南公变,","scope":"浙江省杭州市余杭区仁和街道：双陈村计家坝西南一带","startTime":"2019-09-11 08:20:00","stopDate":"2019-09-11 15:20:00","orgNo":"3340140","typeCode":"计划停电","poweroffArea":"110kV仁镇变:田湾G265线计家坝西南分线6#杆开关","poweroffReason":"杭州地铁10号线仁和车辆段田湾G265线电力迁改工程：拆除田湾G265线计家坝西南分线导线1档，计家坝西南变、计家坝西南1#变配电箱移位2台，新立15米电杆3基及调换低压出线电缆2根工作；","powerTime":"2019-09-11 15:19:00","powerComm":"已送电","subsNo":"","lineNo":"","tgNo":"","tgName":null,"infoStatus":"1","orgName":"国网浙江杭州市余杭区供电有限公司","typeName":null,"infoStatusName":null,"dateDay":null,"orgNos":null,"nowTime":null,"countyName":null,"streetName":null,"villageName":null,"roadName":null,"communityName":null,"tranName":null,"sdLineName":null,"cityCode":"3340140","cityName":"国网浙江杭州市余杭区供电有限公司","provinceCode":null,"stopTime":"2019-09-11 15:20:00","powerType":"全部","powerOffArea":"110kV仁镇变:田湾G265线计家坝西南分线6#杆开关","powerOffReason":"杭州地铁10号线仁和车辆段田湾G265线电力迁改工程：拆除田湾G265线计家坝西南分线导线1档，计家坝西南变、计家坝西南1#变配电箱移位2台，新立15米电杆3基及调换低压出线电缆2根工作；","powerOffId":"2019090231020170"},{"poweroffId":2019090231020162,"sgpoweroffId":null,"subsName":"","lineName":"10kV梅堰G670线","pubTranName":"九曲营路4号公变,梅堰小区6号公变,九曲营路3号公变,梅堰小区十一号公变,杭州市余杭区临平第二小学（6120206038）01号专变,","scope":"浙江省-杭州市-余杭区-东湖街道(梅堰社区-梅堰路,庙前社区-九曲营路);东湖街道-杭州市余杭区临平第二小学一带","startTime":"2019-09-02 13:06:00","stopDate":"2019-09-02 17:06:00","orgNo":"3340140","typeCode":"电网故障停限电","poweroffArea":"110kV南苑变:梅堰G670线曲东开关站曲东开关站梅堰分支箱分线后段","poweroffReason":"高压开关跳闸","powerTime":"2019-09-02 16:14:00","powerComm":"已送电","subsNo":"","lineNo":"","tgNo":"","tgName":null,"infoStatus":"1","orgName":"国网浙江杭州市余杭区供电有限公司","typeName":null,"infoStatusName":null,"dateDay":null,"orgNos":null,"nowTime":null,"countyName":null,"streetName":null,"villageName":null,"roadName":null,"communityName":null,"tranName":null,"sdLineName":null,"cityCode":"3340140","cityName":"国网浙江杭州市余杭区供电有限公司","provinceCode":null,"stopTime":"2019-09-02 17:06:00","powerType":"全部","powerOffArea":"110kV南苑变:梅堰G670线曲东开关站曲东开关站梅堰分支箱分线后段","powerOffReason":"高压开关跳闸","powerOffId":"2019090231020162"},{"poweroffId":2019090231020158,"sgpoweroffId":null,"subsName":"","lineName":"10kV石珠T451线","pubTranName":"文昌苑1号公变,","scope":"浙江省-杭州市-桐庐县-城南街道-梅林社区-学圣路、文昌苑小区、丰汇公寓","startTime":"2019-09-02 12:45:30","stopDate":"2019-09-02 16:30:30","orgNo":"3340150","typeCode":"电网故障停限电","poweroffArea":"110kV下杭变:石珠T451线-文昌苑1号公变后段","poweroffReason":"(低压停电信息)低压开关跳闸","powerTime":"2019-09-02 16:02:44","powerComm":"已送电.","subsNo":"","lineNo":"","tgNo":"","tgName":null,"infoStatus":"1","orgName":"国网浙江桐庐县供电公司","typeName":null,"infoStatusName":null,"dateDay":null,"orgNos":null,"nowTime":null,"countyName":null,"streetName":null,"villageName":null,"roadName":null,"communityName":null,"tranName":null,"sdLineName":null,"cityCode":"3340150","cityName":"国网浙江桐庐县供电公司","provinceCode":null,"stopTime":"2019-09-02 16:30:30","powerType":"全部","powerOffArea":"110kV下杭变:石珠T451线-文昌苑1号公变后段","powerOffReason":"(低压停电信息)低压开关跳闸","powerOffId":"2019090231020158"},{"poweroffId":2019090231020147,"sgpoweroffId":null,"subsName":"","lineName":"10kV安镇Y331线","pubTranName":"安仁村窑棚后台区,","scope":"浙江省-杭州市-建德市-乾潭镇-安仁行政村 安仁自然村,荻州自然村 金秋街一带用户","startTime":"2019-09-02 12:11:00","stopDate":"2019-09-02 13:30:00","orgNo":"3340180","typeCode":"电网故障停限电","poweroffArea":"110kV钦堂变:安镇Y331线-安仁村窑棚后台区后段","poweroffReason":"(低压停电信息)低压开关跳闸 原预计停电结束时间15:00，由于施工现场环境比较复杂，存在不确定因素，因此预估施工时间适当放长了，目前故障已修复，现将停电时间变更至13:30。","powerTime":"2019-09-02 12:56:00","powerComm":"已送电","subsNo":"","lineNo":"","tgNo":"","tgName":null,"infoStatus":"1","orgName":"国网浙江建德市供电有限公司","typeName":null,"infoStatusName":null,"dateDay":null,"orgNos":null,"nowTime":null,"countyName":null,"streetName":null,"villageName":null,"roadName":null,"communityName":null,"tranName":null,"sdLineName":null,"cityCode":"3340180","cityName":"国网浙江建德市供电有限公司","provinceCode":null,"stopTime":"2019-09-02 13:30:00","powerType":"全部","powerOffArea":"110kV钦堂变:安镇Y331线-安仁村窑棚后台区后段","powerOffReason":"(低压停电信息)低压开关跳闸 原预计停电结束时间15:00，由于施工现场环境比较复杂，存在不确定因素，因此预估施工时间适当放长了，目前故障已修复，现将停电时间变更至13:30。","powerOffId":"2019090231020147"},{"poweroffId":2019090231020144,"sgpoweroffId":null,"subsName":"","lineName":"10kV至南T162线","pubTranName":"桃源1号公变,","scope":"浙江省-杭州市-桐庐县-瑶琳镇(桃源行政村-瑶桃路,姚村行政村-皇瑶路)","startTime":"2019-09-02 11:56:47","stopDate":"2019-09-02 15:56:47","orgNo":"3340150","typeCode":"电网故障停限电","poweroffArea":"35kV瑶琳变:至南T162线-桃源1号公变后段","poweroffReason":"(低压停电信息)低压开关跳闸","powerTime":"2019-09-02 15:29:56","powerComm":"已送电.","subsNo":"","lineNo":"","tgNo":"","tgName":null,"infoStatus":"1","orgName":"国网浙江桐庐县供电公司","typeName":null,"infoStatusName":null,"dateDay":null,"orgNos":null,"nowTime":null,"countyName":null,"streetName":null,"villageName":null,"roadName":null,"communityName":null,"tranName":null,"sdLineName":null,"cityCode":"3340150","cityName":"国网浙江桐庐县供电公司","provinceCode":null,"stopTime":"2019-09-02 15:56:47","powerType":"全部","powerOffArea":"35kV瑶琳变:至南T162线-桃源1号公变后段","powerOffReason":"(低压停电信息)低压开关跳闸","powerOffId":"2019090231020144"},{"poweroffId":2019090231020129,"sgpoweroffId":null,"subsName":"","lineName":"10kV芝溪T380线","pubTranName":"春江景苑4号公变,","scope":"浙江省-杭州市-桐庐县-城南街道-上杭社区-龙潭路、春江景苑二期18幢3单元","startTime":"2019-09-02 11:22:07","stopDate":"2019-09-02 13:00:07","orgNo":"3340150","typeCode":"电网故障停限电","poweroffArea":"110kV迎春变:芝溪T380线-春江景苑4号公变后段","poweroffReason":"(低压停电信息)低压开关跳闸","powerTime":"2019-09-02 12:20:32","powerComm":"已送电","subsNo":"","lineNo":"","tgNo":"","tgName":null,"infoStatus":"1","orgName":"国网浙江桐庐县供电公司","typeName":null,"infoStatusName":null,"dateDay":null,"orgNos":null,"nowTime":null,"countyName":null,"streetName":null,"villageName":null,"roadName":null,"communityName":null,"tranName":null,"sdLineName":null,"cityCode":"3340150","cityName":"国网浙江桐庐县供电公司","provinceCode":null,"stopTime":"2019-09-02 13:00:07","powerType":"全部","powerOffArea":"110kV迎春变:芝溪T380线-春江景苑4号公变后段","powerOffReason":"(低压停电信息)低压开关跳闸","powerOffId":"2019090231020129"},{"poweroffId":2019090231020110,"sgpoweroffId":null,"subsName":"","lineName":"10kV石珠T451线","pubTranName":"文昌苑1号公变,","scope":"浙江省-杭州市-桐庐县-城南街道-梅林社区-学圣路、文昌苑小区","startTime":"2019-09-02 10:27:26","stopDate":"2019-09-02 12:27:26","orgNo":"3340150","typeCode":"电网故障停限电","poweroffArea":"110kV下杭变:石珠T451线-文昌苑1号公变后段","poweroffReason":"(低压停电信息)低压开关跳闸","powerTime":"2019-09-02 12:04:27","powerComm":"已送电","subsNo":"","lineNo":"","tgNo":"","tgName":null,"infoStatus":"1","orgName":"国网浙江桐庐县供电公司","typeName":null,"infoStatusName":null,"dateDay":null,"orgNos":null,"nowTime":null,"countyName":null,"streetName":null,"villageName":null,"roadName":null,"communityName":null,"tranName":null,"sdLineName":null,"cityCode":"3340150","cityName":"国网浙江桐庐县供电公司","provinceCode":null,"stopTime":"2019-09-02 12:27:26","powerType":"全部","powerOffArea":"110kV下杭变:石珠T451线-文昌苑1号公变后段","powerOffReason":"(低压停电信息)低压开关跳闸","powerOffId":"2019090231020110"},{"poweroffId":2019090231020092,"sgpoweroffId":null,"subsName":"","lineName":"10kV缤星9710线","pubTranName":"缤纷五变,","scope":"浙江省-杭州市-滨江区-西兴街道-水电社区-丹枫路","startTime":"2019-09-02 09:51:02","stopDate":"2019-09-02 15:51:02","orgNo":"3340101","typeCode":"电网故障停限电","poweroffArea":"110kV府前变:缤星9710线-缤纷五变后段","poweroffReason":"(低压停电信息)低压开关跳闸","powerTime":"2019-09-02 15:06:13","powerComm":"已送电","subsNo":"","lineNo":"","tgNo":"","tgName":null,"infoStatus":"1","orgName":"浙江杭州电力客户服务中心","typeName":null,"infoStatusName":null,"dateDay":null,"orgNos":null,"nowTime":null,"countyName":null,"streetName":null,"villageName":null,"roadName":null,"communityName":null,"tranName":null,"sdLineName":null,"cityCode":"3340101","cityName":"浙江杭州电力客户服务中心","provinceCode":null,"stopTime":"2019-09-02 15:51:02","powerType":"全部","powerOffArea":"110kV府前变:缤星9710线-缤纷五变后段","powerOffReason":"(低压停电信息)低压开关跳闸","powerOffId":"2019090231020092"},{"poweroffId":2019090231020080,"sgpoweroffId":null,"subsName":"","lineName":"10kV上营V145线","pubTranName":"上营村,","scope":"浙江省-杭州市-临安市(昌化镇-上营行政村-上营自然村,龙岗镇-上营行政村-上营自然村)","startTime":"2019-09-02 09:34:00","stopDate":"2019-09-02 13:00:00","orgNo":"3340160","typeCode":"电网故障停限电","poweroffArea":"110kV龙岗变:上营V145线上营村配变","poweroffReason":"高压开关跳闸","powerTime":"2019-09-02 12:45:46","powerComm":"已送电","subsNo":"","lineNo":"","tgNo":"","tgName":null,"infoStatus":"1","orgName":"国网浙江临安市供电公司","typeName":null,"infoStatusName":null,"dateDay":null,"orgNos":null,"nowTime":null,"countyName":null,"streetName":null,"villageName":null,"roadName":null,"communityName":null,"tranName":null,"sdLineName":null,"cityCode":"3340160","cityName":"国网浙江临安市供电公司","provinceCode":null,"stopTime":"2019-09-02 13:00:00","powerType":"全部","powerOffArea":"110kV龙岗变:上营V145线上营村配变","powerOffReason":"高压开关跳闸","powerOffId":"2019090231020080"},{"poweroffId":2019090231020067,"sgpoweroffId":null,"subsName":"","lineName":"10kV新镇C620线","pubTranName":"双圩村1#变,","scope":"浙江省-杭州市-萧山区-新街镇、新街街道-双圩行政村-双圩自然村等一带","startTime":"2019-09-02 09:20:09","stopDate":"2019-09-02 11:20:09","orgNo":"3340130","typeCode":"电网故障停限电","poweroffArea":"110kV新街变:新镇C620线-双圩1#台区低压开关","poweroffReason":"(低压停电信息)低压开关跳闸","powerTime":"2019-09-02 10:24:10","powerComm":"已送电","subsNo":"","lineNo":"","tgNo":"","tgName":null,"infoStatus":"1","orgName":"国网浙江杭州市萧山区供电有限公司","typeName":null,"infoStatusName":null,"dateDay":null,"orgNos":null,"nowTime":null,"countyName":null,"streetName":null,"villageName":null,"roadName":null,"communityName":null,"tranName":null,"sdLineName":null,"cityCode":"3340130","cityName":"国网浙江杭州市萧山区供电有限公司","provinceCode":null,"stopTime":"2019-09-02 11:20:09","powerType":"全部","powerOffArea":"110kV新街变:新镇C620线-双圩1#台区低压开关","powerOffReason":"(低压停电信息)低压开关跳闸","powerOffId":"2019090231020067"}],"pageModel":{"pageNow":1162,"totalCount":17789,"totalPage":1779,"tableRows":0,"pageCount":10,"beginCount":11610},"isExperi":"1"}