{"message":"","today":"2020-06-15","seleList":[{"poweroffId":2020042431020292,"sgpoweroffId":null,"subsName":"","lineName":"10kV图山D502线","pubTranName":"白石胶村2号村边公变,","scope":"浙江省-杭州市-富阳区-场口镇-白石胶行政村-白石胶自然村一带","startTime":"2020-05-08 08:30:00","stopDate":"2020-05-08 15:30:00","orgNo":"3340170","typeCode":"计划停电","poweroffArea":"110kV常安变:图山D502线-白石胶村2号村边公变低压出线后段","poweroffReason":"(低压停电信息)场口2020年青江新区1#公变等台区10千伏增容布点工程：白石胶村2#村边公变3#开关3#出线0#杆-8#杆之间新立电杆1支，新出低压电缆2根及上杆搭接，拆除低压电缆1根，安装终端、互感器等工作。","powerTime":"2020-05-08 15:18:50","powerComm":"已送电","subsNo":"","lineNo":"","tgNo":"","tgName":null,"infoStatus":"1","orgName":"国网浙江杭州市富阳区供电公司","typeName":null,"infoStatusName":null,"dateDay":null,"orgNos":null,"nowTime":null,"countyName":null,"streetName":null,"villageName":null,"roadName":null,"communityName":null,"tranName":null,"sdLineName":null,"cityCode":"3340170","cityName":"国网浙江杭州市富阳区供电公司","provinceCode":null,"stopTime":"2020-05-08 15:30:00","powerType":"全部","powerOffArea":"110kV常安变:图山D502线-白石胶村2号村边公变低压出线后段","powerOffReason":"(低压停电信息)场口2020年青江新区1#公变等台区10千伏增容布点工程：白石胶村2#村边公变3#开关3#出线0#杆-8#杆之间新立电杆1支，新出低压电缆2根及上杆搭接，拆除低压电缆1根，安装终端、互感器等工作。","powerOffId":"2020042431020292"},{"poweroffId":2020042431020286,"sgpoweroffId":null,"subsName":"","lineName":"10kV店口D941线","pubTranName":"店口村5#亭桥头2公变,","scope":"浙江省-杭州市-富阳区-富春街道-三桥行政村(店口自然村,亭桥头自然村)","startTime":"2020-05-07 08:00:00","stopDate":"2020-05-07 16:40:00","orgNo":"3340170","typeCode":"计划停电","poweroffArea":"110kV育才变:店口D941线-店口村5#亭桥头后段","poweroffReason":"(低压停电信息)青云2020年龙星村5#罗家岭公变等低压线路改造照明2#线更换落户线2处，照明3#线更换落户线4处，照明4#线更换落户线6处，照明5#线更换落户线4处，搭接等工作","powerTime":"2020-05-07 16:17:23","powerComm":"已送电","subsNo":"","lineNo":"","tgNo":"","tgName":null,"infoStatus":"1","orgName":"国网浙江杭州市富阳区供电公司","typeName":null,"infoStatusName":null,"dateDay":null,"orgNos":null,"nowTime":null,"countyName":null,"streetName":null,"villageName":null,"roadName":null,"communityName":null,"tranName":null,"sdLineName":null,"cityCode":"3340170","cityName":"国网浙江杭州市富阳区供电公司","provinceCode":null,"stopTime":"2020-05-07 16:40:00","powerType":"全部","powerOffArea":"110kV育才变:店口D941线-店口村5#亭桥头后段","powerOffReason":"(低压停电信息)青云2020年龙星村5#罗家岭公变等低压线路改造照明2#线更换落户线2处，照明3#线更换落户线4处，照明4#线更换落户线6处，照明5#线更换落户线4处，搭接等工作","powerOffId":"2020042431020286"},{"poweroffId":2020042431020285,"sgpoweroffId":null,"subsName":"","lineName":"10kV双林D786线","pubTranName":"真佳溪19#后溪村中公变,","scope":"浙江省-杭州市-富阳区-场口镇-真佳溪行政村-后溪自然村一带","startTime":"2020-05-07 08:30:00","stopDate":"2020-05-07 14:10:00","orgNo":"3340170","typeCode":"计划停电","poweroffArea":"110kV王洲变:双林D786线-真佳溪19#后溪村中公变低压出线后段","poweroffReason":"(低压停电信息)配电屏抬高、低压出线电缆拆装、脚手架拆除等工作；","powerTime":"2020-05-07 13:45:12","powerComm":"已送电","subsNo":"","lineNo":"","tgNo":"","tgName":null,"infoStatus":"1","orgName":"国网浙江杭州市富阳区供电公司","typeName":null,"infoStatusName":null,"dateDay":null,"orgNos":null,"nowTime":null,"countyName":null,"streetName":null,"villageName":null,"roadName":null,"communityName":null,"tranName":null,"sdLineName":null,"cityCode":"3340170","cityName":"国网浙江杭州市富阳区供电公司","provinceCode":null,"stopTime":"2020-05-07 14:10:00","powerType":"全部","powerOffArea":"110kV王洲变:双林D786线-真佳溪19#后溪村中公变低压出线后段","powerOffReason":"(低压停电信息)配电屏抬高、低压出线电缆拆装、脚手架拆除等工作；","powerOffId":"2020042431020285"},{"poweroffId":2020042431020284,"sgpoweroffId":null,"subsName":"","lineName":"10kV双林D786线","pubTranName":"真佳溪村1#后溪桥头公变,","scope":"浙江省-杭州市-富阳区-场口镇-真佳溪行政村-后溪自然村一带","startTime":"2020-05-07 08:30:00","stopDate":"2020-05-07 13:00:00","orgNo":"3340170","typeCode":"计划停电","poweroffArea":"110kV王洲变:双林D786线-真佳溪村1#后溪桥头公变低压出线后段","poweroffReason":"(低压停电信息)塘东畈22号路南侧道路新建工程-电缆管道及电力迁改工程：真佳溪村1#后溪桥头山公变1#开关1#出线2#杆-3#杆之间新立电杆1支，拆除电杆2支，线路改接及表计拆移等工作。","powerTime":"2020-05-07 12:35:27","powerComm":"已送电","subsNo":"","lineNo":"","tgNo":"","tgName":null,"infoStatus":"1","orgName":"国网浙江杭州市富阳区供电公司","typeName":null,"infoStatusName":null,"dateDay":null,"orgNos":null,"nowTime":null,"countyName":null,"streetName":null,"villageName":null,"roadName":null,"communityName":null,"tranName":null,"sdLineName":null,"cityCode":"3340170","cityName":"国网浙江杭州市富阳区供电公司","provinceCode":null,"stopTime":"2020-05-07 13:00:00","powerType":"全部","powerOffArea":"110kV王洲变:双林D786线-真佳溪村1#后溪桥头公变低压出线后段","powerOffReason":"(低压停电信息)塘东畈22号路南侧道路新建工程-电缆管道及电力迁改工程：真佳溪村1#后溪桥头山公变1#开关1#出线2#杆-3#杆之间新立电杆1支，拆除电杆2支，线路改接及表计拆移等工作。","powerOffId":"2020042431020284"},{"poweroffId":2020042431020283,"sgpoweroffId":null,"subsName":"","lineName":"10kV店口D941线","pubTranName":"店口村8号村委旁公变,","scope":"浙江省-杭州市-富阳区-富春街道-三桥行政村-店口自然村","startTime":"2020-05-06 12:30:00","stopDate":"2020-05-06 16:40:00","orgNo":"3340170","typeCode":"计划停电","poweroffArea":"110kV育才变:店口D941线-店口村8号村委旁后段","poweroffReason":"(低压停电信息)青云2020年龙星村5#罗家岭公变等低压线路改造工程更换落户线6处，搭接等工作","powerTime":"2020-05-06 16:30:14","powerComm":"已送电","subsNo":"","lineNo":"","tgNo":"","tgName":null,"infoStatus":"1","orgName":"国网浙江杭州市富阳区供电公司","typeName":null,"infoStatusName":null,"dateDay":null,"orgNos":null,"nowTime":null,"countyName":null,"streetName":null,"villageName":null,"roadName":null,"communityName":null,"tranName":null,"sdLineName":null,"cityCode":"3340170","cityName":"国网浙江杭州市富阳区供电公司","provinceCode":null,"stopTime":"2020-05-06 16:40:00","powerType":"全部","powerOffArea":"110kV育才变:店口D941线-店口村8号村委旁后段","powerOffReason":"(低压停电信息)青云2020年龙星村5#罗家岭公变等低压线路改造工程更换落户线6处，搭接等工作","powerOffId":"2020042431020283"},{"poweroffId":2020042431020282,"sgpoweroffId":null,"subsName":"","lineName":"10kV店口D941线","pubTranName":"店口村2#亭桥头公变,","scope":"浙江省-杭州市-富阳区-富春街道-三桥行政村(店口自然村,亭桥头自然村)","startTime":"2020-05-06 08:00:00","stopDate":"2020-05-06 12:00:00","orgNo":"3340170","typeCode":"计划停电","poweroffArea":"110kV育才变:店口D941线-店口村2#亭桥头后段","poweroffReason":"(低压停电信息)青云2020年龙星村5#罗家岭公变等低压线路改造工程照明3#线更换落户线3处，拆旧，架设1kV70*4-136米，搭接等工作","powerTime":"2020-05-06 11:50:11","powerComm":"已送电","subsNo":"","lineNo":"","tgNo":"","tgName":null,"infoStatus":"1","orgName":"国网浙江杭州市富阳区供电公司","typeName":null,"infoStatusName":null,"dateDay":null,"orgNos":null,"nowTime":null,"countyName":null,"streetName":null,"villageName":null,"roadName":null,"communityName":null,"tranName":null,"sdLineName":null,"cityCode":"3340170","cityName":"国网浙江杭州市富阳区供电公司","provinceCode":null,"stopTime":"2020-05-06 12:00:00","powerType":"全部","powerOffArea":"110kV育才变:店口D941线-店口村2#亭桥头后段","powerOffReason":"(低压停电信息)青云2020年龙星村5#罗家岭公变等低压线路改造工程照明3#线更换落户线3处，拆旧，架设1kV70*4-136米，搭接等工作","powerOffId":"2020042431020282"},{"poweroffId":2020042431020242,"sgpoweroffId":null,"subsName":"","lineName":"10kV胜峰T335线","pubTranName":"大会山1号公变,","scope":"浙江省-杭州市-桐庐县-横村镇-白云行政村-大会山自然村","startTime":"2020-04-24 12:28:08","stopDate":"2020-04-24 17:30:08","orgNo":"3340150","typeCode":"电网故障停限电","poweroffArea":"110kV横村变:胜峰T335线-大会山1号公变后段","poweroffReason":"(低压停电信息)低压开关跳闸","powerTime":"2020-04-24 17:10:51","powerComm":"已送电","subsNo":"","lineNo":"","tgNo":"","tgName":null,"infoStatus":"1","orgName":"国网浙江桐庐县供电公司","typeName":null,"infoStatusName":null,"dateDay":null,"orgNos":null,"nowTime":null,"countyName":null,"streetName":null,"villageName":null,"roadName":null,"communityName":null,"tranName":null,"sdLineName":null,"cityCode":"3340150","cityName":"国网浙江桐庐县供电公司","provinceCode":null,"stopTime":"2020-04-24 17:30:08","powerType":"全部","powerOffArea":"110kV横村变:胜峰T335线-大会山1号公变后段","powerOffReason":"(低压停电信息)低压开关跳闸","powerOffId":"2020042431020242"},{"poweroffId":2020042431020234,"sgpoweroffId":null,"subsName":"","lineName":"10kV青何D731线","pubTranName":"唐昌村青山1#石家公变,","scope":"浙江省-杭州市-富阳区-永昌镇-唐昌行政村-青山石家自然村一带","startTime":"2020-05-07 08:00:00","stopDate":"2020-05-07 16:30:00","orgNo":"3340170","typeCode":"计划停电","poweroffArea":"110kV松溪变:青何D731线-唐昌村青山1#石家公变低压开关后段","poweroffReason":"(低压停电信息)旧照明01线拆除JKLYJ-4*120*2档、照明02线拆除JKLYJ-4*120*3档 、3#杆拆除杆上表计2只。新照明01线2#杆后段架设JKLYJ-4*120*2档、导线搭接1处。","powerTime":"2020-05-07 16:07:13","powerComm":"已送电","subsNo":"","lineNo":"","tgNo":"","tgName":null,"infoStatus":"1","orgName":"国网浙江杭州市富阳区供电公司","typeName":null,"infoStatusName":null,"dateDay":null,"orgNos":null,"nowTime":null,"countyName":null,"streetName":null,"villageName":null,"roadName":null,"communityName":null,"tranName":null,"sdLineName":null,"cityCode":"3340170","cityName":"国网浙江杭州市富阳区供电公司","provinceCode":null,"stopTime":"2020-05-07 16:30:00","powerType":"全部","powerOffArea":"110kV松溪变:青何D731线-唐昌村青山1#石家公变低压开关后段","powerOffReason":"(低压停电信息)旧照明01线拆除JKLYJ-4*120*2档、照明02线拆除JKLYJ-4*120*3档 、3#杆拆除杆上表计2只。新照明01线2#杆后段架设JKLYJ-4*120*2档、导线搭接1处。","powerOffId":"2020042431020234"},{"poweroffId":2020042431020207,"sgpoweroffId":null,"subsName":"","lineName":"10kV新渌D834线","pubTranName":"新浦村五连1#江边公变,","scope":"浙江省-杭州市-富阳区-渌渚镇-新浦行政村-五连江边自然村一带","startTime":"2020-05-10 08:30:00","stopDate":"2020-05-10 16:30:00","orgNo":"3340170","typeCode":"计划停电","poweroffArea":"110kV新桐变:新渌D834线-新浦村五连1#江边公变低压开关后段","poweroffReason":"(低压停电信息)新登2020年10kV董湾D147线、10kV新阳D841线等线路联络工程：10kV新阳D841线、桐浦D844线双回路及10kV新渌D834线、新浦D845线双回路架线、钢管塔组立等工作","powerTime":"2020-05-10 16:15:01","powerComm":"已送电","subsNo":"","lineNo":"","tgNo":"","tgName":null,"infoStatus":"1","orgName":"国网浙江杭州市富阳区供电公司","typeName":null,"infoStatusName":null,"dateDay":null,"orgNos":null,"nowTime":null,"countyName":null,"streetName":null,"villageName":null,"roadName":null,"communityName":null,"tranName":null,"sdLineName":null,"cityCode":"3340170","cityName":"国网浙江杭州市富阳区供电公司","provinceCode":null,"stopTime":"2020-05-10 16:30:00","powerType":"全部","powerOffArea":"110kV新桐变:新渌D834线-新浦村五连1#江边公变低压开关后段","powerOffReason":"(低压停电信息)新登2020年10kV董湾D147线、10kV新阳D841线等线路联络工程：10kV新阳D841线、桐浦D844线双回路及10kV新渌D834线、新浦D845线双回路架线、钢管塔组立等工作","powerOffId":"2020042431020207"},{"poweroffId":2020042431020201,"sgpoweroffId":null,"subsName":"","lineName":"10kV蓝顿8520线","pubTranName":"紫金二,","scope":"浙江省-杭州市-西湖区-紫金公寓小区3幢、7幢、8幢、12幢一带用户及商铺","startTime":"2020-05-09 09:30:00","stopDate":"2020-05-09 13:00:00","orgNo":"3340101","typeCode":"计划停电","poweroffArea":"110kV文三变:蓝顿8520线-紫金二后段","poweroffReason":"紫金小区等0.4kvT接箱更换工程/1811HZ18010601A0000000紫金二0.4kv改造 原停电结束时间为2020-05-09 17:00:00,为减少客户停电时间,加快工作进度,提前送电,现变更停电结束时间为2020-05-09 13:00:00","powerTime":"2020-05-09 12:31:56","powerComm":"已送电","subsNo":"","lineNo":"","tgNo":"","tgName":null,"infoStatus":"1","orgName":"浙江杭州电力客户服务中心","typeName":null,"infoStatusName":null,"dateDay":null,"orgNos":null,"nowTime":null,"countyName":null,"streetName":null,"villageName":null,"roadName":null,"communityName":null,"tranName":null,"sdLineName":null,"cityCode":"3340101","cityName":"浙江杭州电力客户服务中心","provinceCode":null,"stopTime":"2020-05-09 13:00:00","powerType":"全部","powerOffArea":"110kV文三变:蓝顿8520线-紫金二后段","powerOffReason":"紫金小区等0.4kvT接箱更换工程/1811HZ18010601A0000000紫金二0.4kv改造 原停电结束时间为2020-05-09 17:00:00,为减少客户停电时间,加快工作进度,提前送电,现变更停电结束时间为2020-05-09 13:00:00","powerOffId":"2020042431020201"}],"pageModel":{"pageNow":290,"totalCount":17788,"totalPage":1779,"tableRows":0,"pageCount":10,"beginCount":2890},"isExperi":"1"}