{"message":"","today":"2020-06-15","seleList":[{"poweroffId":2020041731020185,"sgpoweroffId":null,"subsName":"","lineName":"10kV新座8508线","pubTranName":"丹桂,","scope":"浙江省-杭州市-西湖区-文新街道-桂花园社区-文三西路","startTime":"2020-04-17 10:58:00","stopDate":"2020-04-17 12:58:00","orgNo":"3340101","typeCode":"电网故障停限电","poweroffArea":"110kV文三变:新座8508线丹桂配变","poweroffReason":"高压开关跳闸","powerTime":"2020-04-17 11:59:09","powerComm":"已送电","subsNo":"","lineNo":"","tgNo":"","tgName":null,"infoStatus":"1","orgName":"浙江杭州电力客户服务中心","typeName":null,"infoStatusName":null,"dateDay":null,"orgNos":null,"nowTime":null,"countyName":null,"streetName":null,"villageName":null,"roadName":null,"communityName":null,"tranName":null,"sdLineName":null,"cityCode":"3340101","cityName":"浙江杭州电力客户服务中心","provinceCode":null,"stopTime":"2020-04-17 12:58:00","powerType":"全部","powerOffArea":"110kV文三变:新座8508线丹桂配变","powerOffReason":"高压开关跳闸","powerOffId":"2020041731020185"},{"poweroffId":2020041731020180,"sgpoweroffId":null,"subsName":"","lineName":"10kV新座8508线","pubTranName":"金桂,","scope":"浙江省-杭州市-西湖区-文新街道-桂花园社区-文三西路","startTime":"2020-04-17 10:50:00","stopDate":"2020-04-17 12:50:00","orgNo":"3340101","typeCode":"电网故障停限电","poweroffArea":"110kV文三变:新座8508线金桂配变","poweroffReason":"高压开关跳闸","powerTime":"2020-04-17 11:53:09","powerComm":"已送电","subsNo":"","lineNo":"","tgNo":"","tgName":null,"infoStatus":"1","orgName":"浙江杭州电力客户服务中心","typeName":null,"infoStatusName":null,"dateDay":null,"orgNos":null,"nowTime":null,"countyName":null,"streetName":null,"villageName":null,"roadName":null,"communityName":null,"tranName":null,"sdLineName":null,"cityCode":"3340101","cityName":"浙江杭州电力客户服务中心","provinceCode":null,"stopTime":"2020-04-17 12:50:00","powerType":"全部","powerOffArea":"110kV文三变:新座8508线金桂配变","powerOffReason":"高压开关跳闸","powerOffId":"2020041731020180"},{"poweroffId":2020041731020175,"sgpoweroffId":null,"subsName":"","lineName":"10kV新春D938线","pubTranName":"新春村19号新区南公变,","scope":"浙江省-杭州市-富阳区-富春街道-杨清庙行政村-南山下自然村","startTime":"2020-04-27 08:20:00","stopDate":"2020-04-27 16:10:00","orgNo":"3340170","typeCode":"计划停电","poweroffArea":"110kV育才变:新春D938线-新春村19号新区南后段","poweroffReason":"(低压停电信息)分支电缆搭接等工作","powerTime":"2020-04-27 16:00:24","powerComm":"已送电","subsNo":"","lineNo":"","tgNo":"","tgName":null,"infoStatus":"1","orgName":"国网浙江杭州市富阳区供电公司","typeName":null,"infoStatusName":null,"dateDay":null,"orgNos":null,"nowTime":null,"countyName":null,"streetName":null,"villageName":null,"roadName":null,"communityName":null,"tranName":null,"sdLineName":null,"cityCode":"3340170","cityName":"国网浙江杭州市富阳区供电公司","provinceCode":null,"stopTime":"2020-04-27 16:10:00","powerType":"全部","powerOffArea":"110kV育才变:新春D938线-新春村19号新区南后段","powerOffReason":"(低压停电信息)分支电缆搭接等工作","powerOffId":"2020041731020175"},{"poweroffId":2020041731020174,"sgpoweroffId":null,"subsName":"","lineName":"10kV店口D941线","pubTranName":"店口村3#店口下公变,","scope":"浙江省-杭州市-富阳区-富春街道-三桥行政村-店口自然村","startTime":"2020-04-27 08:00:00","stopDate":"2020-04-27 11:50:00","orgNo":"3340170","typeCode":"计划停电","poweroffArea":"110kV育才变:店口D941线-店口村3#店口下后段","poweroffReason":"(低压停电信息)青云2020年龙星村5#罗家岭公变等低压线路改造工程更换落户线5处，搭接等工作","powerTime":"2020-04-27 11:40:17","powerComm":"已送电","subsNo":"","lineNo":"","tgNo":"","tgName":null,"infoStatus":"1","orgName":"国网浙江杭州市富阳区供电公司","typeName":null,"infoStatusName":null,"dateDay":null,"orgNos":null,"nowTime":null,"countyName":null,"streetName":null,"villageName":null,"roadName":null,"communityName":null,"tranName":null,"sdLineName":null,"cityCode":"3340170","cityName":"国网浙江杭州市富阳区供电公司","provinceCode":null,"stopTime":"2020-04-27 11:50:00","powerType":"全部","powerOffArea":"110kV育才变:店口D941线-店口村3#店口下后段","powerOffReason":"(低压停电信息)青云2020年龙星村5#罗家岭公变等低压线路改造工程更换落户线5处，搭接等工作","powerOffId":"2020041731020174"},{"poweroffId":2020041731020164,"sgpoweroffId":null,"subsName":"","lineName":"10kV新座8508线","pubTranName":"云桂,","scope":"浙江省-杭州市-西湖区-文新街道-桂花园社区-文三西路云桂花园","startTime":"2020-04-17 10:40:00","stopDate":"2020-04-17 12:40:00","orgNo":"3340101","typeCode":"电网故障停限电","poweroffArea":"110kV文三变:新座8508线云桂配变","poweroffReason":"高压开关跳闸","powerTime":"2020-04-17 12:11:39","powerComm":"已送电","subsNo":"","lineNo":"","tgNo":"","tgName":null,"infoStatus":"1","orgName":"浙江杭州电力客户服务中心","typeName":null,"infoStatusName":null,"dateDay":null,"orgNos":null,"nowTime":null,"countyName":null,"streetName":null,"villageName":null,"roadName":null,"communityName":null,"tranName":null,"sdLineName":null,"cityCode":"3340101","cityName":"浙江杭州电力客户服务中心","provinceCode":null,"stopTime":"2020-04-17 12:40:00","powerType":"全部","powerOffArea":"110kV文三变:新座8508线云桂配变","powerOffReason":"高压开关跳闸","powerOffId":"2020041731020164"},{"poweroffId":2020041731020157,"sgpoweroffId":null,"subsName":"","lineName":"10kV来所A425线","pubTranName":"嘉亭砂石,孔湖村10#变,隧道工程2#,杭州萧山环能实业有限公司,浙江省隧道工程集团有限公司专变,之江有机硅厂,1#,孔湖村4#变,杭州萧山孔湖采石厂,隧道工程1#,杭州萧山万顺液压制动制造厂,孔湖村12#变,杭州万鹏工具制造有限公司,2#,孔湖村7#变,杭州恒宝建材有限公司,牛角钢钉,孔湖村11#变,杭州澳维奇有限公司,孔湖村5#变,孔湖村3#变,杭州金氏钉业有限公司,孔湖采石矿,孔湖村14#变,孔湖村13#变,变压器,杭州方诚工具制造有限公司变压器,杭州市公安局,孔湖采石场,孔湖村2#变,萧山区殡仪馆,孔湖村9#变,章潘桥村立新2#变,变压器,孔湖采石场,","scope":"浙江省-杭州市-萧山区-蜀山街道-章潘桥行政村-立新自然村,所前镇-孔湖行政村(大路张自然村,孔湖自然村,韩家山自然村);蜀山街道-章潘桥行政村(杭州萧山万顺液压制动制造厂,杭州萧山环能实业有限公司,杭州市萧山区殡仪馆),所前镇-孔湖行政村(杭州佳南五金制品有限公司,浙江省隧道工程集团有限公司,杭州万鹏工具制造有限公司,杭州牛角钢钉有限公司,杭州萧山孔湖采石场,来苏孔湖采石场,杭州大路砂石有限公司,杭州金氏钉业有限公司,杭州浙杰钢业有限公司,杭州澳维奇电器有限公司,杭州嘉亭砂石有限公司,杭州萧山国有资产投资有限公司,杭州方诚工具制造有限公司,杭州恒宝建材有限公司),蜀山街道(桥头陈行政村-杭州市公安局,黄家河社区-杭州之江有机硅化工有限公司)，所前镇孔湖村韩家山","startTime":"2020-04-17 10:30:20","stopDate":"2020-04-17 12:30:20","orgNo":"3340130","typeCode":"电网故障停限电","poweroffArea":"110kV来苏变:来所A425线来所A4251开关后段","poweroffReason":"外力破坏引起来所A425线高压柱上断路器短路跳闸","powerTime":"2020-04-17 11:35:19","powerComm":"已送电","subsNo":"","lineNo":"","tgNo":"","tgName":null,"infoStatus":"1","orgName":"国网浙江杭州市萧山区供电有限公司","typeName":null,"infoStatusName":null,"dateDay":null,"orgNos":null,"nowTime":null,"countyName":null,"streetName":null,"villageName":null,"roadName":null,"communityName":null,"tranName":null,"sdLineName":null,"cityCode":"3340130","cityName":"国网浙江杭州市萧山区供电有限公司","provinceCode":null,"stopTime":"2020-04-17 12:30:20","powerType":"全部","powerOffArea":"110kV来苏变:来所A425线来所A4251开关后段","powerOffReason":"外力破坏引起来所A425线高压柱上断路器短路跳闸","powerOffId":"2020041731020157"},{"poweroffId":2020041731020152,"sgpoweroffId":null,"subsName":"","lineName":"10kV塔山H619线","pubTranName":"御景城4号公变,","scope":"浙江省-杭州市-余杭区-余杭街道-南渠社区-禹航路","startTime":"2020-04-17 10:22:00","stopDate":"2020-04-17 11:00:00","orgNo":"3340140","typeCode":"电网故障停限电","poweroffArea":"110kV桃源变:塔山H619线御景城4号公变配变","poweroffReason":"高压开关跳闸原停电结束时间为2020-04-1712:13:00,为减少客户停电时间,加快工作进度,提前送电,现变更停电结束时间为2020-04-1711:00:00","powerTime":"2020-04-17 10:40:03","powerComm":"已送电","subsNo":"","lineNo":"","tgNo":"","tgName":null,"infoStatus":"1","orgName":"国网浙江杭州市余杭区供电有限公司","typeName":null,"infoStatusName":null,"dateDay":null,"orgNos":null,"nowTime":null,"countyName":null,"streetName":null,"villageName":null,"roadName":null,"communityName":null,"tranName":null,"sdLineName":null,"cityCode":"3340140","cityName":"国网浙江杭州市余杭区供电有限公司","provinceCode":null,"stopTime":"2020-04-17 11:00:00","powerType":"全部","powerOffArea":"110kV桃源变:塔山H619线御景城4号公变配变","powerOffReason":"高压开关跳闸原停电结束时间为2020-04-1712:13:00,为减少客户停电时间,加快工作进度,提前送电,现变更停电结束时间为2020-04-1711:00:00","powerOffId":"2020041731020152"},{"poweroffId":2020041731020151,"sgpoweroffId":null,"subsName":"","lineName":"10kV圣堂H509线","pubTranName":"良辰美苑9号公变,良辰美苑12号公变,南山村相公庙1号公变,大观山村良辰美苑3号公变,大观山村良辰美苑7号公变,良辰美苑11号公变,南山新城基建2#变,瓶窑镇政府（港渠路路灯）6120890405,交通项目(南山新城路灯)6120700568,瓶窑镇政府（南山新城2号基建）6120348590,大观山安置点基建（6120877659）01#专变,南山大桥路灯6120601658,大观山村良辰美苑8号公变,大观山安置点基建（6120877659）02#专变,气象局612062971701#专变,基础设施612064451601#专变,良辰美苑1号公变,澄清排涝1,外窑村安置点（6120876938）02#专变,良辰美苑10号公变,澄清排涝2,大观山村良辰美苑4号公变,外窑村安置点（6120876938）01#专变,西溪小学基建02#专变,大观山村良辰美苑5号公变,良辰美苑2号公变,大观山村良辰美苑6号公变,西溪小学基建01#专变,","scope":"浙江省-杭州市-余杭区-瓶窑镇-大观山行政村(凤溪路,良辰美苑,华兴路),瓶窑镇-南山行政村(相公庙自然村,南山自然村,上塘湾自然村);瓶窑镇(杭州市余杭区瓶窑镇人民政府,杭州余杭区交通项目管理有限公司,杭州市余杭区气象局)","startTime":"2020-04-17 10:16:00","stopDate":"2020-04-17 11:50:00","orgNo":"3340140","typeCode":"电网故障停限电","poweroffArea":"35kV瓶镇变:圣堂H509线南山新城分线26#开关后段","poweroffReason":"高压开关跳闸","powerTime":"2020-04-17 11:20:00","powerComm":"已送电","subsNo":"","lineNo":"","tgNo":"","tgName":null,"infoStatus":"1","orgName":"国网浙江杭州市余杭区供电有限公司","typeName":null,"infoStatusName":null,"dateDay":null,"orgNos":null,"nowTime":null,"countyName":null,"streetName":null,"villageName":null,"roadName":null,"communityName":null,"tranName":null,"sdLineName":null,"cityCode":"3340140","cityName":"国网浙江杭州市余杭区供电有限公司","provinceCode":null,"stopTime":"2020-04-17 11:50:00","powerType":"全部","powerOffArea":"35kV瓶镇变:圣堂H509线南山新城分线26#开关后段","powerOffReason":"高压开关跳闸","powerOffId":"2020041731020151"},{"poweroffId":2020041731020133,"sgpoweroffId":null,"subsName":"","lineName":"10kV高水164线","pubTranName":"姚村毛山5号公变,","scope":"浙江省-杭州市-桐庐县-瑶琳镇-姚村行政村-沈村自然村","startTime":"2020-04-17 10:05:00","stopDate":"2020-04-17 12:57:00","orgNo":"3340150","typeCode":"电网故障停限电","poweroffArea":"35kV瑶琳变:高水164线姚村毛山5号公变配变","poweroffReason":"(低压停电信息)低压开关跳闸","powerTime":"2020-04-17 12:26:18","powerComm":"已送电","subsNo":"","lineNo":"","tgNo":"","tgName":null,"infoStatus":"1","orgName":"国网浙江桐庐县供电公司","typeName":null,"infoStatusName":null,"dateDay":null,"orgNos":null,"nowTime":null,"countyName":null,"streetName":null,"villageName":null,"roadName":null,"communityName":null,"tranName":null,"sdLineName":null,"cityCode":"3340150","cityName":"国网浙江桐庐县供电公司","provinceCode":null,"stopTime":"2020-04-17 12:57:00","powerType":"全部","powerOffArea":"35kV瑶琳变:高水164线姚村毛山5号公变配变","powerOffReason":"(低压停电信息)低压开关跳闸","powerOffId":"2020041731020133"},{"poweroffId":2020041731020130,"sgpoweroffId":null,"subsName":"","lineName":"10kV留泗8856线","pubTranName":"里村,","scope":"浙江省-杭州市-西湖区-留下街道-东穆坞里村一带","startTime":"2020-04-24 09:30:00","stopDate":"2020-04-24 15:00:00","orgNo":"3340101","typeCode":"临时停电","poweroffArea":"110kV留下变:留泗8856线-里村后段","poweroffReason":"石马新村等小区设备改造工程PD2020-04-023-WJP新设公变1台 原停电结束时间为2020-04-24 17:00:00,为减少客户停电时间,加快工作进度,提前送电,现变更停电结束时间为2020-04-24 15:00:00","powerTime":"2020-04-24 14:20:56","powerComm":"已送电","subsNo":"","lineNo":"","tgNo":"","tgName":null,"infoStatus":"1","orgName":"浙江杭州电力客户服务中心","typeName":null,"infoStatusName":null,"dateDay":null,"orgNos":null,"nowTime":null,"countyName":null,"streetName":null,"villageName":null,"roadName":null,"communityName":null,"tranName":null,"sdLineName":null,"cityCode":"3340101","cityName":"浙江杭州电力客户服务中心","provinceCode":null,"stopTime":"2020-04-24 15:00:00","powerType":"全部","powerOffArea":"110kV留下变:留泗8856线-里村后段","powerOffReason":"石马新村等小区设备改造工程PD2020-04-023-WJP新设公变1台 原停电结束时间为2020-04-24 17:00:00,为减少客户停电时间,加快工作进度,提前送电,现变更停电结束时间为2020-04-24 15:00:00","powerOffId":"2020041731020130"}],"pageModel":{"pageNow":327,"totalCount":17788,"totalPage":1779,"tableRows":0,"pageCount":10,"beginCount":3260},"isExperi":"1"}